pythonlinux/__init__.py
pythonlinux/pythonlinux.py
qimomo_py_linux-0.1.5.dist-info/licenses/LICENSE
qimomo_py_linux-0.1.5.dist-info/METADATA
qimomo_py_linux-0.1.5.dist-info/WHEEL
qimomo_py_linux-0.1.5.dist-info/top_level.txt
qimomo_py_linux-0.1.5.dist-info/RECORD
