Metadata-Version: 2.4
Name: qimomo-py-linux
Version: 0.1.5
Summary: pythonlinux python中简单运行linux命令
Author-email: qimomo <qimomo.17@qq.com>
License: Copyright 2025 七魔陌
Classifier: License :: OSI Approved :: BSD License
Classifier: Programming Language :: Python :: 3
Classifier: Operating System :: OS Independent
Classifier: Development Status :: 4 - Beta
License-File: LICENSE
Requires-Dist: requests>=2.25.1
Requires-Dist: tqdm
Dynamic: license-file
